mcap_ros2/__init__.py
mcap_ros2/_cdr.py
mcap_ros2/_dynamic.py
mcap_ros2/decoder.py
mcap_ros2/py.typed
mcap_ros2/reader.py
mcap_ros2/writer.py
mcap_ros2/_vendor/__init__.py
mcap_ros2/_vendor/rosidl_adapter/__init__.py
mcap_ros2/_vendor/rosidl_adapter/parser.py
tests/__init__.py
tests/generate.py
tests/test_cdr_reader.py
tests/test_cdr_writer.py
tests/test_ros2_decoder.py
tests/test_ros2_writer.py
mcap_ros2_support-0.5.3.dist-info/METADATA
mcap_ros2_support-0.5.3.dist-info/WHEEL
mcap_ros2_support-0.5.3.dist-info/top_level.txt
mcap_ros2_support-0.5.3.dist-info/RECORD
