Metadata-Version: 2.1
Name: mcap-ros2-support
Version: 0.5.3
Summary: ROS2 support for the Python MCAP library
Home-page: https://github.com/foxglove/mcap
Classifier: Programming Language :: Python :: 3
Classifier: License :: OSI Approved :: MIT License
Classifier: Operating System :: OS Independent
Requires-Python: >=3.7
Requires-Dist: mcap >=0.0.14
